vmine/__init__.py
vmine/__main__.py
vmine/main.py
vmine/plugins/__init__.py
vmine/plugins/cseffects/__init__.py
vmine/plugins/cseffects/hat.png
vmine/plugins/cseffects/plugin.cp37-win32.pyd
vmine/plugins/cseffects/plugin.py
vmine/plugins/cseffects/shape_predictor_5_face_landmarks.dat
vmine-1.0.0.1.dist-info/METADATA
vmine-1.0.0.1.dist-info/WHEEL
vmine-1.0.0.1.dist-info/entry_points.txt
vmine-1.0.0.1.dist-info/top_level.txt
vmine-1.0.0.1.dist-info/RECORD
